[ 
    { 
        "author" : "Horohoro", 
        "name" : "letest", 
        "keyWords" : "couleur,bleu,blue,color", 
        "version" : "1.0.0", 
        "dofusVersion" : "2.37", 
        "description" : "voir si sa marche", 
        "url" : "https://github.com/Nkeyza/testthemeun/raw/master/themepokemon.zip", 
        "previewUrl" : "http://ordre2vlad.fr/dofusthemes/images/preview/blueStone.png", 
        "creationDate" : "23/10/2016", 
        "modificationDate" : "23/10/2016" 
    } 
]
